tas/__init__.py
tas/drama.py
tas/server.py
tas/story.py
tas/types.py
tas/world.py
tas/css/tas.css
tas/dlg/00_introduction.rst
tas/dlg/01_inception.rst
tas/dlg/02_elaboration.rst
tas/dlg/03_construction.rst
tas/dlg/04_transition.rst
tas/dlg/05_completion.rst
tas/dlg/06_discussion.rst
tas/dlg/07_defaulted.rst
tas/dlg/08_withdrawn.rst
tas/dlg/09_cancelled.rst
tas/dlg/10_resolution.rst
tas/dlg/11_conclusion.rst
tas/dlg/12_intervention.rst
tas/dlg/__init__.py
tas/test/__init__.py
tas/test/test_sympathy.py
tea_and_sympathy-0.17.0.dist-info/LICENSE
tea_and_sympathy-0.17.0.dist-info/METADATA
tea_and_sympathy-0.17.0.dist-info/WHEEL
tea_and_sympathy-0.17.0.dist-info/entry_points.txt
tea_and_sympathy-0.17.0.dist-info/top_level.txt
tea_and_sympathy-0.17.0.dist-info/zip-safe
tea_and_sympathy-0.17.0.dist-info/RECORD
